integracio/__init__.py
integracio/_cgracio_d.cp36-win_amd64.pyd
integracio/_cgracio_f.cp36-win_amd64.pyd
integracio/igracio.py
integracio/poni.py
integracio/utils.py
integracio-2018.7.18.dist-info/METADATA
integracio-2018.7.18.dist-info/RECORD
integracio-2018.7.18.dist-info/WHEEL
integracio-2018.7.18.dist-info/top_level.txt
